ocpi_client-0.1.15.dist-info/METADATA
ocpi_client-0.1.15.dist-info/WHEEL
ocpi_client-0.1.15.dist-info/entry_points.txt
ocpi_client-0.1.15.dist-info/licenses/LICENSE
ocpi_client/__init__.py
ocpi_client/logging.py
ocpi_client/models.py
ocpi_client-0.1.15.dist-info/RECORD
